vvmtools/__init__.py
vvmtools/analyze/__init__.py
vvmtools/analyze/core.py
vvmtools/plot/__init__.py
vvmtools/plot/core.py
vvmtools-1.1.0.dist-info/LICENSE
vvmtools-1.1.0.dist-info/METADATA
vvmtools-1.1.0.dist-info/WHEEL
vvmtools-1.1.0.dist-info/top_level.txt
vvmtools-1.1.0.dist-info/RECORD
